{
  "timestamp": "2025-10-09T17:38:44",
  "policy": "sarsa",
  "seed": 0,
  "mode": "auto-stop",
  "episodes_total": 2600,
  "steps_cap_per_episode": 40,
  "successes": 1821,
  "success_rate_pct": 70.04,
  "mean_reward": 837.477,
  "mean_steps": 31.233,
  "reward_trend": "improving",
  "success_trend": "improving",
  "maturity_eval_based": "Developing",
  "auto_stop_target_pct": 80.0,
  "auto_stop_achieved": true,
  "episodes_at_target": 2600,
  "phases": [
    {
      "phase_index": 1,
      "episodes": 200,
      "success_rate_pct": 65.5,
      "mean_reward": 762.369,
      "mean_steps": 32.665,
      "eval_success_rate_pct": 60.0,
      "eval_mean_reward": 787.6,
      "checkpoint": "checkpoints/sarsa_ep200.pkl",
      "trend_fig": "trace_results/figs/trend_phase1_ep200.png"
    },
    {
      "phase_index": 2,
      "episodes": 200,
      "success_rate_pct": 61.0,
      "mean_reward": 782.401,
      "mean_steps": 32.145,
      "eval_success_rate_pct": 58.0,
      "eval_mean_reward": 777.6,
      "checkpoint": "checkpoints/sarsa_ep400.pkl",
      "trend_fig": "trace_results/figs/trend_phase2_ep200.png"
    },
    {
      "phase_index": 3,
      "episodes": 200,
      "success_rate_pct": 69.5,
      "mean_reward": 792.039,
      "mean_steps": 31.47,
      "eval_success_rate_pct": 54.0,
      "eval_mean_reward": 798.1,
      "checkpoint": "checkpoints/sarsa_ep600.pkl",
      "trend_fig": "trace_results/figs/trend_phase3_ep200.png"
    },
    {
      "phase_index": 4,
      "episodes": 200,
      "success_rate_pct": 70.5,
      "mean_reward": 797.76,
      "mean_steps": 31.23,
      "eval_success_rate_pct": 68.0,
      "eval_mean_reward": 799.1,
      "checkpoint": "checkpoints/sarsa_ep800.pkl",
      "trend_fig": "trace_results/figs/trend_phase4_ep200.png"
    },
    {
      "phase_index": 5,
      "episodes": 200,
      "success_rate_pct": 65.0,
      "mean_reward": 812.324,
      "mean_steps": 31.895,
      "eval_success_rate_pct": 66.0,
      "eval_mean_reward": 826.3,
      "checkpoint": "checkpoints/sarsa_ep1000.pkl",
      "trend_fig": "trace_results/figs/trend_phase5_ep200.png"
    },
    {
      "phase_index": 6,
      "episodes": 200,
      "success_rate_pct": 71.0,
      "mean_reward": 856.615,
      "mean_steps": 31.63,
      "eval_success_rate_pct": 70.0,
      "eval_mean_reward": 881.1,
      "checkpoint": "checkpoints/sarsa_ep1200.pkl",
      "trend_fig": "trace_results/figs/trend_phase6_ep200.png"
    },
    {
      "phase_index": 7,
      "episodes": 200,
      "success_rate_pct": 67.5,
      "mean_reward": 875.897,
      "mean_steps": 32.375,
      "eval_success_rate_pct": 72.0,
      "eval_mean_reward": 910.7,
      "checkpoint": "checkpoints/sarsa_ep1400.pkl",
      "trend_fig": "trace_results/figs/trend_phase7_ep200.png"
    },
    {
      "phase_index": 8,
      "episodes": 200,
      "success_rate_pct": 74.5,
      "mean_reward": 868.691,
      "mean_steps": 31.185,
      "eval_success_rate_pct": 74.0,
      "eval_mean_reward": 898.6,
      "checkpoint": "checkpoints/sarsa_ep1600.pkl",
      "trend_fig": "trace_results/figs/trend_phase8_ep200.png"
    },
    {
      "phase_index": 9,
      "episodes": 200,
      "success_rate_pct": 64.5,
      "mean_reward": 885.237,
      "mean_steps": 31.88,
      "eval_success_rate_pct": 68.0,
      "eval_mean_reward": 882.9,
      "checkpoint": "checkpoints/sarsa_ep1800.pkl",
      "trend_fig": "trace_results/figs/trend_phase9_ep200.png"
    },
    {
      "phase_index": 10,
      "episodes": 200,
      "success_rate_pct": 68.5,
      "mean_reward": 871.515,
      "mean_steps": 30.385,
      "eval_success_rate_pct": 70.0,
      "eval_mean_reward": 858.1,
      "checkpoint": "checkpoints/sarsa_ep2000.pkl",
      "trend_fig": "trace_results/figs/trend_phase10_ep200.png"
    },
    {
      "phase_index": 11,
      "episodes": 200,
      "success_rate_pct": 73.0,
      "mean_reward": 866.022,
      "mean_steps": 30.07,
      "eval_success_rate_pct": 78.0,
      "eval_mean_reward": 893.3,
      "checkpoint": "checkpoints/sarsa_ep2200.pkl",
      "trend_fig": "trace_results/figs/trend_phase11_ep200.png"
    },
    {
      "phase_index": 12,
      "episodes": 200,
      "success_rate_pct": 78.5,
      "mean_reward": 849.996,
      "mean_steps": 29.81,
      "eval_success_rate_pct": 70.0,
      "eval_mean_reward": 883.3,
      "checkpoint": "checkpoints/sarsa_ep2400.pkl",
      "trend_fig": "trace_results/figs/trend_phase12_ep200.png"
    },
    {
      "phase_index": 13,
      "episodes": 200,
      "success_rate_pct": 81.5,
      "mean_reward": 866.33,
      "mean_steps": 29.285,
      "eval_success_rate_pct": 70.0,
      "eval_mean_reward": 920.4,
      "checkpoint": "checkpoints/sarsa_ep2600.pkl",
      "trend_fig": "trace_results/figs/trend_phase13_ep200.png"
    }
  ]
}